{"year": "2019", "level": "Undergraduate Level 3", "code": "ANSC30005", "campus": "Parkville", "availability": "Semester 2", "prerequisites": ["ANSC20001"], "corequisites": "None", "antirequisites": ["ECOL20003", "ANSC20003", "ANSC20005", "ANSC20002"], "name": "Animal Welfare and Ethics", "desc": "Previously\u00a0BIOL30010\nThis subject develops knowledge and understanding of systems for regulating body function, and physiological and behavioural processes that are utilised by animals in response to environmental challenges. This basis will allow students to evaluate and assess animal welfare a..."}