{"year": "2019", "level": "Undergraduate Level 2", "code": "COMP20008", "campus": "Parkville", "availability": "Semester 1, Semester 2", "prerequisites": ["COMP10001", "COMP10003"], "corequisites": "None", "antirequisites": [], "name": "Elements of Data Processing", "desc": "AIMS\nData processing is fundamental to computing and data science. This subject gives an introduction to various aspects of data processing including database management, representation and analysis of data, information retrieval, visualisation and reporting, and cloud computing. This subject in..."}