{"year": "2019", "level": "Undergraduate Level 3", "code": "CRIM30006", "campus": "Parkville", "availability": "Semester 1", "prerequisites": [], "corequisites": "None", "antirequisites": [], "name": "Crime and Culture", "desc": "Cinema and television have become immensely popular and influential cultural forms. This subject investigates the relationship between crime and culture by focusing on representations of crime and justice in film and television. The subject considers these representations in the context of recent..."}