{"year": "2019", "level": "Honours", "code": "CRIM40003", "campus": "Parkville", "availability": "Semester 1", "prerequisites": [], "corequisites": "None", "antirequisites": [], "name": "Drugs and Justice", "desc": "This subject introduces students to a range of historical and contemporary issues surrounding the measurement of drug use and the popular and scientific construction of the health, crime and social consequences of drug use. The subject is concerned with the relationships between various construct..."}