{"year": "2019", "level": "Undergraduate Level 2", "code": "EDUC20085", "campus": "Parkville", "availability": "Semester 1", "prerequisites": [], "corequisites": "None", "antirequisites": [], "name": "Singing, Song Writing and Youth Music", "desc": "Singing and song writing (including rap and hip hop) play an important role in lives of young people, impacting on their personal and social identity formation by providing a creative vehicle to connect with others, express and generate meaning. Through practical music and arts activities, resear..."}