{"year": "2019", "level": "Honours", "code": "ENGL40026", "campus": "Parkville", "availability": "Semester 1, Semester 2", "prerequisites": ["MULT50001"], "corequisites": "None", "antirequisites": ["ENGL40023 "], "name": "English & Theatre Studies Thesis Part 1", "desc": "Topics selected in consultation with the coordinator. Enrolment in the thesis is across two consecutive semesters and students must enrol in the subject in each semester to ensure they are meeting the full 50 point requirement for the year-long subject."}