{"year": "2019", "level": "Undergraduate Level 3", "code": "FRST30003", "campus": "Parkville", "availability": "Semester 1", "prerequisites": ["BIOL10001", "BIOL10002", "BIOL10003", "BIOL10004", "BIOL10005", "LARC10001", "HORT20026"], "corequisites": "None", "antirequisites": [], "name": "Urban Forest Ecosystems", "desc": "This subject imparts detailed knowledge on the crucial role that urban forests are playing in the development and resilience of sustainable cities around the world, using both local and international case studies. It begins by exploring the unique composition of urban forests, and the multiple so..."}