{"year": "2019", "level": "Undergraduate Level 3", "code": "GERM30001", "campus": "Parkville", "availability": "Semester 1, Semester 2", "prerequisites": ["GERM10002", "GERM20005", "GERM10007", "GERM20008", "GERM30006"], "corequisites": "None", "antirequisites": ["GERM20003"], "name": "German Cultural Studies B", "desc": "This subject consists of area studies relating to aspects of modern German literature, linguistics, and cultural studies. Students will do intensive studies, including a range of representative texts, authors or approaches in a key area of German literature, linguistics and cultural studies from ..."}