{"year": "2019", "level": "Undergraduate Level 2", "code": "HIST20068", "campus": "Parkville", "availability": "Semester 2", "prerequisites": [], "corequisites": "None", "antirequisites": [], "name": "The French Revolution", "desc": "In 1789 huge numbers of French peasants, urban workers and middle-class people successfully rebelled against absolute monarchy and the privileges of the nobility. But the struggle over what social and political system should replace the 'Old Regime' was to divide French people and finally the who..."}