{"year": "2019", "level": "Undergraduate Level 2", "code": "MAST20030", "campus": "Parkville", "availability": "Semester 2", "prerequisites": ["MAST20009", "MAST10007", "MAST10008", "MAST10018 ", "MAST10013 ", "MAST10006", "MAST10009", "MAST10019 "], "corequisites": "None", "antirequisites": [], "name": "Differential Equations", "desc": "Differential equations arise as common models in the physical, mathematical, biological and engineering sciences. This subject covers linear differential equations, both ordinary and partial, using concepts from linear algebra to provide the general structure of solutions for ordinary differentia..."}