{"year": "2019", "level": "Honours", "code": "MIIM40007", "campus": "Parkville", "availability": "Semester 1", "prerequisites": [], "corequisites": " ", "antirequisites": ["MIIM40002", "MIIM40005"], "name": "Advanced Microbiology and Immunology II", "desc": "To become effective research scientists, students need to develop the skills such as critical review and analysis of data, appropriate design and execution of experiments, appropriate documentation of experimental plans and results, interpretation of data and presentation and communication of dat..."}