{"year": "2019", "level": "Undergraduate Level 2", "code": "MUSI20164", "campus": "Southbank", "availability": "Semester 1, Semester 2", "prerequisites": [], "corequisites": "None", "antirequisites": [], "name": "Free Play New Music Improvisation Ensem", "desc": "This subject gives participants the opportunity for an in-depth practical study of musical improvisation techniques by introducing the participant to the marvellous and unique art of improvisation. This performance-based subject introduces the practice of musical improvisation for those musicians..."}