{"year": "2019", "level": "Undergraduate Level 2", "code": "MUSI20212", "campus": "Southbank", "availability": "Semester 2", "prerequisites": [], "corequisites": "None", "antirequisites": ["Practical Anatomy for Classical Voice 1 "], "name": "Practical Anatomy for Classical Voice 2", "desc": "This subject explores the making of sound from a physiological standpoint and tackles the many questions posed in the study of classical singing. Through both lectures and practical exploration, the subject explores the translation of multilingual singing imagery and terminology into singing prac..."}